d_flip_flop.v
//this module implements d flip flop using behavioural approach
module d_flip_flop(input d,input clk, input reset,output reg q, output reg qb);
always @(posedge clk or posedge reset)
    begin
        if (reset)
        begin
            q = 1'b0; 
            qb= 1'b1; 
        end
        else
        begin
            q=d; 
            qb=~q; 
        end
    end
endmodule

MOD_12_counter.v
//Code for Mod12COunter Implementation in FPGA
module mod12counter(
    input clk,reset,
    output [3:0]q,
    output reg [7:0] segment,
    output reg [3:0] ctrl
);

wire [3:0]qb;
wire w1,w2,w3,w4,w5,w6,w7,w8,w9;
integer i,j; 
reg clkdiv, clkdiv2, flag; 

initial begin
		i = 0;
		j = 0;
		clkdiv = 1'b0;
		clkdiv2 = 1'b0;
		flag = 1'b0;
end

always @(posedge clk) begin
	i = i+1; j = j+1;
	if (i == 1000) begin
		clkdiv = ~clkdiv;
		i = 0;
	end
	if (j == 1) begin
		clkdiv2 = ~clkdiv2;
		j = 0;
	end
end

always@(posedge clkdiv2) begin
	if (flag == 1'b0) begin
		ctrl = 4'b0111;
		case (q)
			4'd0:segment=8'b11111100;
			4'd1:segment=8'b01100000; 
			4'd2:segment=8'b11011010;  
			4'd3:segment=8'b11110010; 
			4'd4:segment=8'b01100110; 
			4'd5:segment=8'b10110110; 
			4'd6:segment=8'b10111110; 
			4'd7:segment=8'b11100000; 
			4'd8:segment=8'b11111110; 
			4'd9:segment=8'b11110110;  
			4'd10:segment=8'b11111100;
			4'd11:segment=8'b01100000;
			4'd12:segment=8'b01100000; 
		endcase
		flag = 1'b1;
	end
	else begin
        ctrl = 4'b1011;
		case (q)
			4'd10:segment=8'b01100000;
			4'd11:segment=8'b01100000; 
			4'd12:segment=8'b01100000;  
			default: segment=8'b11111100;       
		endcase
		flag = 1'b0;
	end
end


//Structure of MOD_12_counter
d_flip_flop dff0(qb[0],clkdiv,reset,q[0],qb[0]);
xor x0(w1 ,q[0],q[1]);
d_flip_flop dff1(w1,clkdiv,reset,q[1],qb[1]);

and a0(w2,q[2],qb[1]);
and a1(w3,q[2],qb[0]);
and a2(w4,qb[3],qb[2],q[1],q[0]);
or o1(w5,w2,w3,w4);

d_flip_flop dff2(w5,clkdiv,reset,q[2],qb[2]);

and a3(w6,q[3],qb[1]);
and a4(w7,q[3],qb[0]);
and a5(w8,q[2],q[1],q[0]);
or o2(w9,w6,w7,w8);

d_flip_flop dff3(w9,clkdiv,reset,q[3],qb[3]);

endmodule

testbench.v
module testbench;

    reg clk, reset;
    wire [3:0] q, ctrl;
    wire [7:0] segment ;

    mod12counter dut(clk, reset, q, segment, ctrl);

    always #1 clk = ~clk;

    initial begin
        $dumpfile("testbench.vcd");
        $dumpvars(0,testbench);
        clk <= 1'b0;
        reset = 1;
        #1 reset = 0;
        $monitor("clk = %d , count = %d\n",clk,q);
    end

    initial #100000 $finish;

endmodule

testbench.vcd
$date
	Mon Oct 09 17:24:01 2023
$end
$version
	Icarus Verilog
$end
$timescale
	1s
$end
$scope module testbench $end
$var wire 8 ! segment [7:0] $end
$var wire 4 " q [3:0] $end
$var wire 4 # ctrl [3:0] $end
$var reg 1 $ clk $end
$var reg 1 % reset $end
$scope module dut $end
$var wire 1 $ clk $end
$var wire 1 % reset $end
$var wire 1 & w1 $end
$var wire 1 ' w2 $end
$var wire 1 ( w3 $end
$var wire 1 ) w4 $end
$var wire 1 * w5 $end
$var wire 1 + w6 $end
$var wire 1 , w7 $end
$var wire 1 - w8 $end
$var wire 1 . w9 $end
$var wire 4 / qb [3:0] $end
$var wire 4 0 q [3:0] $end
$var reg 1 1 clkdiv $end
$var reg 1 2 clkdiv2 $end
$var reg 4 3 ctrl [3:0] $end
$var reg 1 4 flag $end
$var reg 8 5 segment [7:0] $end
$var integer 32 6 i [31:0] $end
$var integer 32 7 j [31:0] $end
$scope module dff0 $end
$var wire 1 1 clk $end
$var wire 1 8 d $end
$var wire 1 % reset $end
$var reg 1 9 q $end
$var reg 1 : qb $end
$upscope $end
$scope module dff1 $end
$var wire 1 1 clk $end
$var wire 1 & d $end
$var wire 1 % reset $end
$var reg 1 ; q $end
$var reg 1 < qb $end
$upscope $end
$scope module dff2 $end
$var wire 1 1 clk $end
$var wire 1 * d $end
$var wire 1 % reset $end
$var reg 1 = q $end
$var reg 1 > qb $end
$upscope $end
$scope module dff3 $end
$var wire 1 1 clk $end
$var wire 1 . d $end
$var wire 1 % reset $end
$var reg 1 ? q $end
$var reg 1 @ qb $end
$upscope $end
$upscope $end
$upscope $end
$enddefinitions $end
$comment Show the parameter values. $end
$dumpall
$end
#0
$dumpvars
1@
0?
1>
0=
1<
0;
1:
09
18
b0 7
b0 6
bx 5
04
bx 3
02
01
b0 0
b1111 /
0.
0-
0,
0+
0*
0)
0(
0'
0&
1%
0$
bx #
b0 "
bx !
$end
#1
14
b11111100 !
b11111100 5
b111 #
b111 3
12
b0 7
b1 6
0%
1$
#2
0$
#3
02
b0 7
b10 6
1$
#4
0$
#5
04
b1011 #
b1011 3
12
b0 7
b11 6
1$
#6
0$
#7
02
b0 7
b100 6
1$
#8
0$
#9
14
b111 #
b111 3
12
b0 7
b101 6
1$
#10
0$
#11
02
b0 7
b110 6
1$
#12
0$
#13
04
b1011 #
b1011 3
12
b0 7
b111 6
1$
#14
0$
#15
02
b0 7
b1000 6
1$
#16
0$
#17
14
b111 #
b111 3
12
b0 7
b1001 6
1$
#18
0$
#19
02
b0 7
b1010 6
1$
#20
0$
#21
04
b1011 #
b1011 3
12
b0 7
b1011 6
1$
#22
0$
#23
02
b0 7
b1100 6
1$
#24
0$
#25
14
b111 #
b111 3
12
b0 7
b1101 6
1$
#26
0$
#27
02
b0 7
b1110 6
1$
#28
0$
#29
04
b1011 #
b1011 3
12
b0 7
b1111 6
1$
#30
0$
#31
02
b0 7
b10000 6
1$
#32
0$
#33
14
b111 #
b111 3
12
b0 7
b10001 6
1$
#34
0$
#35
02
b0 7
b10010 6
1$
#36
0$
#37
04
b1011 #
b1011 3
12
b0 7
b10011 6
1$
#38
0$
#39
02
b0 7
b10100 6
1$
#40
0$
#41
14
b111 #
b111 3
12
b0 7
b10101 6
1$
#42
0$
#43
02
b0 7
b10110 6
1$
#44
0$
#45
04
b1011 #
b1011 3
12
b0 7
b10111 6
1$
#46
0$
#47
02
b0 7
b11000 6
1$
#48
0$
#49
14
b111 #
b111 3
12
b0 7
b11001 6
1$
#50
0$
#51
02
b0 7
b11010 6
1$
#52
0$
#53
04
b1011 #
b1011 3
12
b0 7
b11011 6
1$
#54
0$
#55
02
b0 7
b11100 6
1$
#56
0$
#57
14
b111 #
b111 3
12
b0 7
b11101 6
1$
#58
0$
#59
02
b0 7
b11110 6
1$
#60
0$
#61
04
b1011 #
b1011 3
12
b0 7
b11111 6
1$
#62
0$
#63
02
b0 7
b100000 6
1$
#64
0$
#65
14
b111 #
b111 3
12
b0 7
b100001 6
1$
#66
0$
#67
02
b0 7
b100010 6
1$
#68
0$
#69
04
b1011 #
b1011 3
12
b0 7
b100011 6
1$
#70
0$
#71
02
b0 7
b100100 6
1$
#72
0$
#73
14
b111 #
b111 3
12
b0 7
b100101 6
1$
#74
0$
#75
02
b0 7
b100110 6
1$
#76
0$
#77
04
b1011 #
b1011 3
12
b0 7
b100111 6
1$
#78
0$
#79
02
b0 7
b101000 6
1$
#80
0$
#81
14
b111 #
b111 3
12
b0 7
b101001 6
1$
#82
0$
#83
02
b0 7
b101010 6
1$
#84
0$
#85
04
b1011 #
b1011 3
12
b0 7
b101011 6
1$
#86
0$
#87
02
b0 7
b101100 6
1$
#88
0$
#89
14
b111 #
b111 3
12
b0 7
b101101 6
1$
#90
0$
#91
02
b0 7
b101110 6
1$
#92
0$
#93
04
b1011 #
b1011 3
12
b0 7
b101111 6
1$
#94
0$
#95
02
b0 7
b110000 6
1$
#96
0$
#97
14
b111 #
b111 3
12
b0 7
b110001 6
1$
#98
0$
#99
02
b0 7
b110010 6
1$
#100
0$
#101
04
b1011 #
b1011 3
12
b0 7
b110011 6
1$
#102
0$
#103
02
b0 7
b110100 6
1$
#104
0$
#105
14
b111 #
b111 3
12
b0 7
b110101 6
1$
#106
0$
#107
02
b0 7
b110110 6
1$
#108
0$
#109
04
b1011 #
b1011 3
12
b0 7
b110111 6
1$
#110
0$
#111
02
b0 7
b111000 6
1$
#112
0$
#113
14
b111 #
b111 3
12
b0 7
b111001 6
1$
#114
0$
#115
02
b0 7
b111010 6
1$
#116
0$
#117
04
b1011 #
b1011 3
12
b0 7
b111011 6
1$
#118
0$
#119
02
b0 7
b111100 6
1$
#120
0$
#121
14
b111 #
b111 3
12
b0 7
b111101 6
1$
#122
0$
#123
02
b0 7
b111110 6
1$
#124
0$
#125
04
b1011 #
b1011 3
12
b0 7
b111111 6
1$
#126
0$
#127
02
b0 7
b1000000 6
1$
#128
0$
#129
14
b111 #
b111 3
12
b0 7
b1000001 6
1$
#130
0$
#131
02
b0 7
b1000010 6
1$
#132
0$
#133
04
b1011 #
b1011 3
12
b0 7
b1000011 6
1$
#134
0$
#135
02
b0 7
b1000100 6
1$
#136
0$
#137
14
b111 #
b111 3
12
b0 7
b1000101 6
1$
#138
0$
#139
02
b0 7
b1000110 6
1$
#140
0$
#141
04
b1011 #
b1011 3
12
b0 7
b1000111 6
1$
#142
0$
#143
02
b0 7
b1001000 6
1$
#144
0$
#145
14
b111 #
b111 3
12
b0 7
b1001001 6
1$
#146
0$
#147
02
b0 7
b1001010 6
1$
#148
0$
#149
04
b1011 #
b1011 3
12
b0 7
b1001011 6
1$
#150
0$
#151
02
b0 7
b1001100 6
1$
#152
0$
#153
14
b111 #
b111 3
12
b0 7
b1001101 6
1$
#154
0$
#155
02
b0 7
b1001110 6
1$
#156
0$
#157
04
b1011 #
b1011 3
12
b0 7
b1001111 6
1$
#158
0$
#159
02
b0 7
b1010000 6
1$
#160
0$
#161
14
b111 #
b111 3
12
b0 7
b1010001 6
1$
#162
0$
#163
02
b0 7
b1010010 6
1$
#164
0$
#165
04
b1011 #
b1011 3
12
b0 7
b1010011 6
1$
#166
0$
#167
02
b0 7
b1010100 6
1$
#168
0$
#169
14
b111 #
b111 3
12
b0 7
b1010101 6
1$
#170
0$
#171
02
b0 7
b1010110 6
1$
#172
0$
#173
04
b1011 #
b1011 3
12
b0 7
b1010111 6
1$
#174
0$
#175
02
b0 7
b1011000 6
1$
#176
0$
#177
14
b111 #
b111 3
12
b0 7
b1011001 6
1$
#178
0$
#179
02
b0 7
b1011010 6
1$
#180
0$
#181
04
b1011 #
b1011 3
12
b0 7
b1011011 6
1$
#182
0$
#183
02
b0 7
b1011100 6
1$
#184
0$
#185
14
b111 #
b111 3
12
b0 7
b1011101 6
1$
#186
0$
#187
02
b0 7
b1011110 6
1$
#188
0$
#189
04
b1011 #
b1011 3
12
b0 7
b1011111 6
1$
#190
0$
#191
02
b0 7
b1100000 6
1$
#192
0$
#193
14
b111 #
b111 3
12
b0 7
b1100001 6
1$
#194
0$
#195
02
b0 7
b1100010 6
1$
#196
0$
#197
04
b1011 #
b1011 3
12
b0 7
b1100011 6
1$
#198
0$
#199
02
b0 7
b1100100 6
1$
#200
0$
#201
14
b111 #
b111 3
12
b0 7
b1100101 6
1$
#202
0$
#203
02
b0 7
b1100110 6
1$
#204
0$
#205
04
b1011 #
b1011 3
12
b0 7
b1100111 6
1$
#206
0$
#207
02
b0 7
b1101000 6
1$
#208
0$
#209
14
b111 #
b111 3
12
b0 7
b1101001 6
1$
#210
0$
#211
02
b0 7
b1101010 6
1$
#212
0$
#213
04
b1011 #
b1011 3
12
b0 7
b1101011 6
1$
#214
0$
#215
02
b0 7
b1101100 6
1$
#216
0$
#217
14
b111 #
b111 3
12
b0 7
b1101101 6
1$
#218
0$
#219
02
b0 7
b1101110 6
1$
#220
0$
#221
04
b1011 #
b1011 3
12
b0 7
b1101111 6
1$
#222
0$
#223
02
b0 7
b1110000 6
1$
#224
0$
#225
14
b111 #
b111 3
12
b0 7
b1110001 6
1$
#226
0$
#227
02
b0 7
b1110010 6
1$
#228
0$
#229
04
b1011 #
b1011 3
12
b0 7
b1110011 6
1$
#230
0$
#231
02
b0 7
b1110100 6
1$
#232
0$
#233
14
b111 #
b111 3
12
b0 7
b1110101 6
1$
#234
0$
#235
02
b0 7
b1110110 6
1$
#236
0$
#237
04
b1011 #
b1011 3
12
b0 7
b1110111 6
1$
#238
0$
#239
02
b0 7
b1111000 6
1$
#240
0$
#241
14
b111 #
b111 3
12
b0 7
b1111001 6
1$
#242
0$
#243
02
b0 7
b1111010 6
1$
#244
0$
#245
04
b1011 #
b1011 3
12
b0 7
b1111011 6
1$
#246
0$
#247
02
b0 7
b1111100 6
1$
#248
0$
#249
14
b111 #
b111 3
12
b0 7
b1111101 6
1$
#250
0$
#251
02
b0 7
b1111110 6
1$
#252
0$
#253
04
b1011 #
b1011 3
12
b0 7
b1111111 6
1$
#254
0$
#255
02
b0 7
b10000000 6
1$
#256
0$
#257
14
b111 #
b111 3
12
b0 7
b10000001 6
1$
#258
0$
#259
02
b0 7
b10000010 6
1$
#260
0$
#261
04
b1011 #
b1011 3
12
b0 7
b10000011 6
1$
#262
0$
#263
02
b0 7
b10000100 6
1$
#264
0$
#265
14
b111 #
b111 3
12
b0 7
b10000101 6
1$
#266
0$
#267
02
b0 7
b10000110 6
1$
#268
0$
#269
04
b1011 #
b1011 3
12
b0 7
b10000111 6
1$
#270
0$
#271
02
b0 7
b10001000 6
1$
#272
0$
#273
14
b111 #
b111 3
12
b0 7
b10001001 6
1$
#274
0$
#275
02
b0 7
b10001010 6
1$
#276
0$
#277
04
b1011 #
b1011 3
12
b0 7
b10001011 6
1$
#278
0$
#279
02
b0 7
b10001100 6
1$
#280
0$
#281
14
b111 #
b111 3
12
b0 7
b10001101 6
1$
#282
0$
#283
02
b0 7
b10001110 6
1$
#284
0$
#285
04
b1011 #
b1011 3
12
b0 7
b10001111 6
1$
#286
0$
#287
02
b0 7
b10010000 6
1$
#288
0$
#289
14
b111 #
b111 3
12
b0 7
b10010001 6
1$
#290
0$
#291
02
b0 7
b10010010 6
1$
#292
0$
#293
04
b1011 #
b1011 3
12
b0 7
b10010011 6
1$
#294
0$
#295
02
b0 7
b10010100 6
1$
#296
0$
#297
14
b111 #
b111 3
12
b0 7
b10010101 6
1$
#298
0$
#299
02
b0 7
b10010110 6
1$
#300
0$
#301
04
b1011 #
b1011 3
12
b0 7
b10010111 6
1$
#302
0$
#303
02
b0 7
b10011000 6
1$
#304
0$
#305
14
b111 #
b111 3
12
b0 7
b10011001 6
1$
#306
0$
#307
02
b0 7
b10011010 6
1$
#308
0$
#309
04
b1011 #
b1011 3
12
b0 7
b10011011 6
1$
#310
0$
#311
02
b0 7
b10011100 6
1$
#312
0$
#313
14
b111 #
b111 3
12
b0 7
b10011101 6
1$
#314
0$
#315
02
b0 7
b10011110 6
1$
#316
0$
#317
04
b1011 #
b1011 3
12
b0 7
b10011111 6
1$
#318
0$
#319
02
b0 7
b10100000 6
1$
#320
0$
#321
14
b111 #
b111 3
12
b0 7
b10100001 6
1$
#322
0$
#323
02
b0 7
b10100010 6
1$
#324
0$
#325
04
b1011 #
b1011 3
12
b0 7
b10100011 6
1$
#326
0$
#327
02
b0 7
b10100100 6
1$
#328
0$
#329
14
b111 #
b111 3
12
b0 7
b10100101 6
1$
#330
0$
#331
02
b0 7
b10100110 6
1$
#332
0$
#333
04
b1011 #
b1011 3
12
b0 7
b10100111 6
1$
#334
0$
#335
02
b0 7
b10101000 6
1$
#336
0$
#337
14
b111 #
b111 3
12
b0 7
b10101001 6
1$
#338
0$
#339
02
b0 7
b10101010 6
1$
#340
0$
#341
04
b1011 #
b1011 3
12
b0 7
b10101011 6
1$
#342
0$
#343
02
b0 7
b10101100 6
1$
#344
0$
#345
14
b111 #
b111 3
12
b0 7
b10101101 6
1$
#346
0$
#347
02
b0 7
b10101110 6
1$
#348
0$
#349
04
b1011 #
b1011 3
12
b0 7
b10101111 6
1$
#350
0$
#351
02
b0 7
b10110000 6
1$
#352
0$
#353
14
b111 #
b111 3
12
b0 7
b10110001 6
1$
#354
0$
#355
02
b0 7
b10110010 6
1$
#356
0$
#357
04
b1011 #
b1011 3
12
b0 7
b10110011 6
1$
#358
0$
#359
02
b0 7
b10110100 6
1$
#360
0$
#361
14
b111 #
b111 3
12
b0 7
b10110101 6
1$
#362
0$
#363
02
b0 7
b10110110 6
1$
#364
0$
#365
04
b1011 #
b1011 3
12
b0 7
b10110111 6
1$
#366
0$
#367
02
b0 7
b10111000 6
1$
#368
0$
#369
14
b111 #
b111 3
12
b0 7
b10111001 6
1$
#370
0$
#371
02
b0 7
b10111010 6
1$
#372
0$
#373
04
b1011 #
b1011 3
12
b0 7
b10111011 6
1$
#374
0$
#375
02
b0 7
b10111100 6
1$
#376
0$
#377
14
b111 #
b111 3
12
b0 7
b10111101 6
1$
#378
0$
#379
02
b0 7
b10111110 6
1$
#380
0$
#381
04
b1011 #
b1011 3
12
b0 7
b10111111 6
1$
#382
0$
#383
02
b0 7
b11000000 6
1$
#384
0$
#385
14
b111 #
b111 3
12
b0 7
b11000001 6
1$
#386
0$
#387
02
b0 7
b11000010 6
1$
#388
0$
#389
04
b1011 #
b1011 3
12
b0 7
b11000011 6
1$
#390
0$
#391
02
b0 7
b11000100 6
1$
#392
0$
#393
14
b111 #
b111 3
12
b0 7
b11000101 6
1$
#394
0$
#395
02
b0 7
b11000110 6
1$
#396
0$
#397
04
b1011 #
b1011 3
12
b0 7
b11000111 6
1$
#398
0$
#399
02
b0 7
b11001000 6
1$
#400
0$
#401
14
b111 #
b111 3
12
b0 7
b11001001 6
1$
#402
0$
#403
02
b0 7
b11001010 6
1$
#404
0$
#405
04
b1011 #
b1011 3
12
b0 7
b11001011 6
1$
#406
0$
#407
02
b0 7
b11001100 6
1$
#408
0$
#409
14
b111 #
b111 3
12
b0 7
b11001101 6
1$
#410
0$
#411
02
b0 7
b11001110 6
1$
#412
0$
#413
04
b1011 #
b1011 3
12
b0 7
b11001111 6
1$
#414
0$
#415
02
b0 7
b11010000 6
1$
#416
0$
#417
14
b111 #
b111 3
12
b0 7
b11010001 6
1$
#418
0$
#419
02
b0 7
b11010010 6
1$
#420
0$
#421
04
b1011 #
b1011 3
12
b0 7
b11010011 6
1$
#422
0$
#423
02
b0 7
b11010100 6
1$
#424
0$
#425
14
b111 #
b111 3
12
b0 7
b11010101 6
1$
#426
0$
#427
02
b0 7
b11010110 6
1$
#428
0$
#429
04
b1011 #
b1011 3
12
b0 7
b11010111 6
1$
#430
0$
#431
02
b0 7
b11011000 6
1$
#432
0$
#433
14
b111 #
b111 3
12
b0 7
b11011001 6
1$
#434
0$
#435
02
b0 7
b11011010 6
1$
#436
0$
#437
04
b1011 #
b1011 3
12
b0 7
b11011011 6
1$
#438
0$
#439
02
b0 7
b11011100 6
1$
#440
0$
#441
14
b111 #
b111 3
12
b0 7
b11011101 6
1$
#442
0$
#443
02
b0 7
b11011110 6
1$
#444
0$
#445
04
b1011 #
b1011 3
12
b0 7
b11011111 6
1$
#446
0$
#447
02
b0 7
b11100000 6
1$
#448
0$
#449
14
b111 #
b111 3
12
b0 7
b11100001 6
1$
#450
0$
#451
02
b0 7
b11100010 6
1$
#452
0$
#453
04
b1011 #
b1011 3
12
b0 7
b11100011 6
1$
#454
0$
#455
02
b0 7
b11100100 6
1$
#456
0$
#457
14
b111 #
b111 3
12
b0 7
b11100101 6
1$
#458
0$
#459
02
b0 7
b11100110 6
1$
#460
0$
#461
04
b1011 #
b1011 3
12
b0 7
b11100111 6
1$
#462
0$
#463
02
b0 7
b11101000 6
1$
#464
0$
#465
14
b111 #
b111 3
12
b0 7
b11101001 6
1$
#466
0$
#467
02
b0 7
b11101010 6
1$
#468
0$
#469
04
b1011 #
b1011 3
12
b0 7
b11101011 6
1$
#470
0$
#471
02
b0 7
b11101100 6
1$
#472
0$
#473
14
b111 #
b111 3
12
b0 7
b11101101 6
1$
#474
0$
#475
02
b0 7
b11101110 6
1$
#476
0$
#477
04
b1011 #
b1011 3
12
b0 7
b11101111 6
1$
#478
0$
#479
02
b0 7
b11110000 6
1$
#480
0$
#481
14
b111 #
b111 3
12
b0 7
b11110001 6
1$
#482
0$
#483
02
b0 7
b11110010 6
1$
#484
0$
#485
04
b1011 #
b1011 3
12
b0 7
b11110011 6
1$
#486
0$
#487
02
b0 7
b11110100 6
1$
#488
0$
#489
14
b111 #
b111 3
12
b0 7
b11110101 6
1$
#490
0$
#491
02
b0 7
b11110110 6
1$
#492
0$
#493
04
b1011 #
b1011 3
12
b0 7
b11110111 6
1$
#494
0$
#495
02
b0 7
b11111000 6
1$
#496
0$
#497
14
b111 #
b111 3
12
b0 7
b11111001 6
1$
#498
0$
#499
02
b0 7
b11111010 6
1$
#500
0$
#501
04
b1011 #
b1011 3
12
b0 7
b11111011 6
1$
#502
0$
#503
02
b0 7
b11111100 6
1$
#504
0$
#505
14
b111 #
b111 3
12
b0 7
b11111101 6
1$
#506
0$
#507
02
b0 7
b11111110 6
1$
#508
0$
#509
04
b1011 #
b1011 3
12
b0 7
b11111111 6
1$
#510
0$
#511
02
b0 7
b100000000 6
1$
#512
0$
#513
14
b111 #
b111 3
12
b0 7
b100000001 6
1$
#514
0$
#515
02
b0 7
b100000010 6
1$
#516
0$
#517
04
b1011 #
b1011 3
12
b0 7
b100000011 6
1$
#518
0$
#519
02
b0 7
b100000100 6
1$
#520
0$
#521
14
b111 #
b111 3
12
b0 7
b100000101 6
1$
#522
0$
#523
02
b0 7
b100000110 6
1$
#524
0$
#525
04
b1011 #
b1011 3
12
b0 7
b100000111 6
1$
#526
0$
#527
02
b0 7
b100001000 6
1$
#528
0$
#529
14
b111 #
b111 3
12
b0 7
b100001001 6
1$
#530
0$
#531
02
b0 7
b100001010 6
1$
#532
0$
#533
04
b1011 #
b1011 3
12
b0 7
b100001011 6
1$
#534
0$
#535
02
b0 7
b100001100 6
1$
#536
0$
#537
14
b111 #
b111 3
12
b0 7
b100001101 6
1$
#538
0$
#539
02
b0 7
b100001110 6
1$
#540
0$
#541
04
b1011 #
b1011 3
12
b0 7
b100001111 6
1$
#542
0$
#543
02
b0 7
b100010000 6
1$
#544
0$
#545
14
b111 #
b111 3
12
b0 7
b100010001 6
1$
#546
0$
#547
02
b0 7
b100010010 6
1$
#548
0$
#549
04
b1011 #
b1011 3
12
b0 7
b100010011 6
1$
#550
0$
#551
02
b0 7
b100010100 6
1$
#552
0$
#553
14
b111 #
b111 3
12
b0 7
b100010101 6
1$
#554
0$
#555
02
b0 7
b100010110 6
1$
#556
0$
#557
04
b1011 #
b1011 3
12
b0 7
b100010111 6
1$
#558
0$
#559
02
b0 7
b100011000 6
1$
#560
0$
#561
14
b111 #
b111 3
12
b0 7
b100011001 6
1$
#562
0$
#563
02
b0 7
b100011010 6
1$
#564
0$
#565
04
b1011 #
b1011 3
12
b0 7
b100011011 6
1$
#566
0$
#567
02
b0 7
b100011100 6
1$
#568
0$
#569
14
b111 #
b111 3
12
b0 7
b100011101 6
1$
#570
0$
#571
02
b0 7
b100011110 6
1$
#572
0$
#573
04
b1011 #
b1011 3
12
b0 7
b100011111 6
1$
#574
0$
#575
02
b0 7
b100100000 6
1$
#576
0$
#577
14
b111 #
b111 3
12
b0 7
b100100001 6
1$
#578
0$
#579
02
b0 7
b100100010 6
1$
#580
0$
#581
04
b1011 #
b1011 3
12
b0 7
b100100011 6
1$
#582
0$
#583
02
b0 7
b100100100 6
1$
#584
0$
#585
14
b111 #
b111 3
12
b0 7
b100100101 6
1$
#586
0$
#587
02
b0 7
b100100110 6
1$
#588
0$
#589
04
b1011 #
b1011 3
12
b0 7
b100100111 6
1$
#590
0$
#591
02
b0 7
b100101000 6
1$
#592
0$
#593
14
b111 #
b111 3
12
b0 7
b100101001 6
1$
#594
0$
#595
02
b0 7
b100101010 6
1$
#596
0$
#597
04
b1011 #
b1011 3
12
b0 7
b100101011 6
1$
#598
0$
#599
02
b0 7
b100101100 6
1$
#600
0$
#601
14
b111 #
b111 3
12
b0 7
b100101101 6
1$
#602
0$
#603
02
b0 7
b100101110 6
1$
#604
0$
#605
04
b1011 #
b1011 3
12
b0 7
b100101111 6
1$
#606
0$
#607
02
b0 7
b100110000 6
1$
#608
0$
#609
14
b111 #
b111 3
12
b0 7
b100110001 6
1$
#610
0$
#611
02
b0 7
b100110010 6
1$
#612
0$
#613
04
b1011 #
b1011 3
12
b0 7
b100110011 6
1$
#614
0$
#615
02
b0 7
b100110100 6
1$
#616
0$
#617
14
b111 #
b111 3
12
b0 7
b100110101 6
1$
#618
0$
#619
02
b0 7
b100110110 6
1$
#620
0$
#621
04
b1011 #
b1011 3
12
b0 7
b100110111 6
1$
#622
0$
#623
02
b0 7
b100111000 6
1$
#624
0$
#625
14
b111 #
b111 3
12
b0 7
b100111001 6
1$
#626
0$
#627
02
b0 7
b100111010 6
1$
#628
0$
#629
04
b1011 #
b1011 3
12
b0 7
b100111011 6
1$
#630
0$
#631
02
b0 7
b100111100 6
1$
#632
0$
#633
14
b111 #
b111 3
12
b0 7
b100111101 6
1$
#634
0$
#635
02
b0 7
b100111110 6
1$
#636
0$
#637
04
b1011 #
b1011 3
12
b0 7
b100111111 6
1$
#638
0$
#639
02
b0 7
b101000000 6
1$
#640
0$
#641
14
b111 #
b111 3
12
b0 7
b101000001 6
1$
#642
0$
#643
02
b0 7
b101000010 6
1$
#644
0$
#645
04
b1011 #
b1011 3
12
b0 7
b101000011 6
1$
#646
0$
#647
02
b0 7
b101000100 6
1$
#648
0$
#649
14
b111 #
b111 3
12
b0 7
b101000101 6
1$
#650
0$
#651
02
b0 7
b101000110 6
1$
#652
0$
#653
04
b1011 #
b1011 3
12
b0 7
b101000111 6
1$
#654
0$
#655
02
b0 7
b101001000 6
1$
#656
0$
#657
14
b111 #
b111 3
12
b0 7
b101001001 6
1$
#658
0$
#659
02
b0 7
b101001010 6
1$
#660
0$
#661
04
b1011 #
b1011 3
12
b0 7
b101001011 6
1$
#662
0$
#663
02
b0 7
b101001100 6
1$
#664
0$
#665
14
b111 #
b111 3
12
b0 7
b101001101 6
1$
#666
0$
#667
02
b0 7
b101001110 6
1$
#668
0$
#669
04
b1011 #
b1011 3
12
b0 7
b101001111 6
1$
#670
0$
#671
02
b0 7
b101010000 6
1$
#672
0$
#673
14
b111 #
b111 3
12
b0 7
b101010001 6
1$
#674
0$
#675
02
b0 7
b101010010 6
1$
#676
0$
#677
04
b1011 #
b1011 3
12
b0 7
b101010011 6
1$
#678
0$
#679
02
b0 7
b101010100 6
1$
#680
0$
#681
14
b111 #
b111 3
12
b0 7
b101010101 6
1$
#682
0$
#683
02
b0 7
b101010110 6
1$
#684
0$
#685
04
b1011 #
b1011 3
12
b0 7
b101010111 6
1$
#686
0$
#687
02
b0 7
b101011000 6
1$
#688
0$
#689
14
b111 #
b111 3
12
b0 7
b101011001 6
1$
#690
0$
#691
02
b0 7
b101011010 6
1$
#692
0$
#693
04
b1011 #
b1011 3
12
b0 7
b101011011 6
1$
#694
0$
#695
02
b0 7
b101011100 6
1$
#696
0$
#697
14
b111 #
b111 3
12
b0 7
b101011101 6
1$
#698
0$
#699
02
b0 7
b101011110 6
1$
#700
0$
#701
04
b1011 #
b1011 3
12
b0 7
b101011111 6
1$
#702
0$
#703
02
b0 7
b101100000 6
1$
#704
0$
#705
14
b111 #
b111 3
12
b0 7
b101100001 6
1$
#706
0$
#707
02
b0 7
b101100010 6
1$
#708
0$
#709
04
b1011 #
b1011 3
12
b0 7
b101100011 6
1$
#710
0$
#711
02
b0 7
b101100100 6
1$
#712
0$
#713
14
b111 #
b111 3
12
b0 7
b101100101 6
1$
#714
0$
#715
02
b0 7
b101100110 6
1$
#716
0$
#717
04
b1011 #
b1011 3
12
b0 7
b101100111 6
1$
#718
0$
#719
02
b0 7
b101101000 6
1$
#720
0$
#721
14
b111 #
b111 3
12
b0 7
b101101001 6
1$
#722
0$
#723
02
b0 7
b101101010 6
1$
#724
0$
#725
04
b1011 #
b1011 3
12
b0 7
b101101011 6
1$
#726
0$
#727
02
b0 7
b101101100 6
1$
#728
0$
#729
14
b111 #
b111 3
12
b0 7
b101101101 6
1$
#730
0$
#731
02
b0 7
b101101110 6
1$
#732
0$
#733
04
b1011 #
b1011 3
12
b0 7
b101101111 6
1$
#734
0$
#735
02
b0 7
b101110000 6
1$
#736
0$
#737
14
b111 #
b111 3
12
b0 7
b101110001 6
1$
#738
0$
#739
02
b0 7
b101110010 6
1$
#740
0$
#741
04
b1011 #
b1011 3
12
b0 7
b101110011 6
1$
#742
0$
#743
02
b0 7
b101110100 6
1$
#744
0$
#745
14
b111 #
b111 3
12
b0 7
b101110101 6
1$
#746
0$
#747
02
b0 7
b101110110 6
1$
#748
0$
#749
04
b1011 #
b1011 3
12
b0 7
b101110111 6
1$
#750
0$
#751
02
b0 7
b101111000 6
1$
#752
0$
#753
14
b111 #
b111 3
12
b0 7
b101111001 6
1$
#754
0$
#755
02
b0 7
b101111010 6
1$
#756
0$
#757
04
b1011 #
b1011 3
12
b0 7
b101111011 6
1$
#758
0$
#759
02
b0 7
b101111100 6
1$
#760
0$
#761
14
b111 #
b111 3
12
b0 7
b101111101 6
1$
#762
0$
#763
02
b0 7
b101111110 6
1$
#764
0$
#765
04
b1011 #
b1011 3
12
b0 7
b101111111 6
1$
#766
0$
#767
02
b0 7
b110000000 6
1$
#768
0$
#769
14
b111 #
b111 3
12
b0 7
b110000001 6
1$
#770
0$
#771
02
b0 7
b110000010 6
1$
#772
0$
#773
04
b1011 #
b1011 3
12
b0 7
b110000011 6
1$
#774
0$
#775
02
b0 7
b110000100 6
1$
#776
0$
#777
14
b111 #
b111 3
12
b0 7
b110000101 6
1$
